floppity/__init__.py
floppity/flappity.py
floppity/helpers.py
floppity/plot_utils.py
floppity/postprocessing.py
floppity/simulators.py
floppity/data/obs_1
floppity/data/obs_2
floppity/data/obs_3
floppity/data/obs_RV_1.txt
floppity/data/obs_RV_2.txt
floppity/data/obs_simple.txt
floppity-0.1.1.dist-info/licenses/LICENSE
floppity-0.1.1.dist-info/METADATA
floppity-0.1.1.dist-info/WHEEL
floppity-0.1.1.dist-info/top_level.txt
floppity-0.1.1.dist-info/RECORD
