Metadata-Version: 2.4
Name: FlopPITy
Version: 0.1.1
Summary: normalising Flow exoPlanet Parameter Inference Toolkyt
Author-email: Francisco Ardevol Martinez <fardevolmartinez@amnh.org>
License-Expression: BSD-3-Clause
Requires-Python: <3.13,>=3.10
License-File: LICENSE
Requires-Dist: numpy<2
Requires-Dist: sbi
Requires-Dist: corner
Requires-Dist: cloudpickle
Dynamic: license-file
